{
  "Calendar": {
    "calendars": [
      {
        "type": "ics",
        "url": ""
      },
      {
        "type": "exchange",
        "credentials": {
          "username": "",
          "password": "",
          "url": "http://example.com/Ews/Exchange.asmx"
        }
      }
    ]
  },
  "Email": {
    "mailboxes": [
      {
        "type": "exchange",
        "credentials": {
          "username": "",
          "password": "",
          "url": "http://example.com/Ews/Exchange.asmx"
        }
      },
      {
        "type": "imap",
        "credentials": {
          "user": "",
          "password": "",
          "host": "imap.gmail.com",
          "port": 993,
          "tls": true
        },
        "flagMailboxName": "[Gmail]/All Mail",
        "unreadMailboxName": "Inbox"
      }
    ]
  },
  "RSS": {
    "max": 10,
    "sets": [
      {
        "title": "News",
        "feeds": [
          "http://rss.nytimes.com/services/xml/rss/nyt/HomePage.xml"
        ]
      },
      {
        "title": "Tech",
        "feeds": [
          "https://news.ycombinator.com/rss"
        ]
      },
      {
        "title": "Open Source",
        "feeds": [
          "http://opensource.com/feed"
        ]
      }
    ]
  },
  "Tasks": {
    "apis": [
      {
        "type": "todoist",
        "token": ""
      },
      {
        "type": "asana",
        "token": ""
      }
    ]
  },
  "Twitter": {
    "credentials": {
      "consumer": {
        "key": "",
        "secret": ""
      },
      "access": {
        "token": "",
        "tokenSecret": ""
      }
    },
    "lists": [
      {
        "owner": "johnjones4",
        "slug": "open-source",
        "title": "Open Source"
      }
    ]
  },
  "Weather": {
    "key": "",
    "location": "22314"
  }
}
